LICENSE
README.md
setup.py
MarkdownToXmind.egg-info/PKG-INFO
MarkdownToXmind.egg-info/SOURCES.txt
MarkdownToXmind.egg-info/dependency_links.txt
MarkdownToXmind.egg-info/top_level.txt
core/MarkdownToXmind.py
core/__init__.py