Metadata-Version: 2.1
Name: MarkdownToXmind
Version: 1.0.1
Summary: 将Markdown文本格式内容转换为较新版本XMind思维导图
Home-page: https://gitee.com/seamam/markdown-to-xmind.git
Author: QingHua.Yao
Author-email: yaohua1179@163.com
License: Apache License
Keywords: MarkdownToXmind,xmind
Classifier: License :: OSI Approved :: Apache Software License
Classifier: Programming Language :: Python :: 3.10
Classifier: Programming Language :: Python :: 3.11
Classifier: Programming Language :: Python :: Implementation :: CPython
Classifier: Programming Language :: Python :: Implementation :: PyPy
Requires-Python: >=3.9, <4
License-File: LICENSE
